cortana/__init__.py
cortana/cortana_agent.py
cortana/PrebuiltTools/__init__.py
cortana/PrebuiltTools/google_tools.py
cortana/utils/__init__.py
cortana/utils/helper_functions.py
cortana_agent-0.1.1.dist-info/METADATA
cortana_agent-0.1.1.dist-info/WHEEL
cortana_agent-0.1.1.dist-info/RECORD
