Metadata-Version: 2.4
Name: cortana-agent
Version: 0.1.1
Summary: Cortana - A Helpful AI Assistant with MCP support, image search, and code execution capabilities
Project-URL: Homepage, https://github.com/yourusername/cortana-agent
Project-URL: Documentation, https://github.com/yourusername/cortana-agent#readme
Project-URL: Repository, https://github.com/yourusername/cortana-agent
Project-URL: Bug Tracker, https://github.com/yourusername/cortana-agent/issues
Author-email: Tristan Padiou <padioutristan@gmail.com>
License: MIT
Keywords: ai,assistant,google-ai,mcp,openai,pydantic-ai
Classifier: Development Status :: 3 - Alpha
Classifier: Intended Audience :: Developers
Classifier: License :: OSI Approved :: MIT License
Classifier: Programming Language :: Python :: 3
Classifier: Programming Language :: Python :: 3.13
Classifier: Topic :: Scientific/Engineering :: Artificial Intelligence
Classifier: Topic :: Software Development :: Libraries :: Python Modules
Requires-Python: >=3.13
Requires-Dist: pydantic-ai>=0.4.0
Requires-Dist: tavily-python>=0.5.1
Provides-Extra: dev
Requires-Dist: black>=22.0; extra == 'dev'
Requires-Dist: flake8>=4.0; extra == 'dev'
Requires-Dist: isort>=5.10; extra == 'dev'
Requires-Dist: mypy>=0.950; extra == 'dev'
Requires-Dist: pre-commit>=2.15; extra == 'dev'
Requires-Dist: pytest-asyncio>=0.18.0; extra == 'dev'
Requires-Dist: pytest>=6.0; extra == 'dev'
